{
	"artifacts" : 
	[
		{
			"path" : "libplay_motion2_msgs__rosidl_typesupport_cpp.so"
		}
	],
	"backtrace" : 6,
	"backtraceGraph" : 
	{
		"commands" : 
		[
			"_add_library",
			"add_library",
			"include",
			"ament_execute_extensions",
			"rosidl_generate_interfaces",
			"_install",
			"ament_cmake_symlink_install_targets",
			"install",
			"target_link_libraries",
			"set_target_properties",
			"_find_package",
			"find_package",
			"add_dependencies",
			"target_compile_options",
			"add_definitions"
		],
		"files" : 
		[
			"/home/hoangkn/Hoang/Tools/vcpkg/scripts/buildsystems/vcpkg.cmake",
			"/opt/ros/jazzy/share/rosidl_typesupport_cpp/cmake/rosidl_typesupport_cpp_generate_interfaces.cmake",
			"/opt/ros/jazzy/share/ament_cmake_core/cmake/core/ament_execute_extensions.cmake",
			"/opt/ros/jazzy/share/rosidl_cmake/cmake/rosidl_generate_interfaces.cmake",
			"CMakeLists.txt",
			"/opt/ros/jazzy/share/ament_cmake_core/cmake/symlink_install/ament_cmake_symlink_install_targets.cmake",
			"/opt/ros/jazzy/share/ament_cmake_core/cmake/symlink_install/install.cmake",
			"/opt/ros/jazzy/share/rosidl_generator_c/cmake/rosidl_generator_c_generate_interfaces.cmake",
			"/opt/ros/jazzy/share/rcutils/cmake/rcutilsExport.cmake",
			"/opt/ros/jazzy/share/rcutils/cmake/ament_cmake_export_targets-extras.cmake",
			"/opt/ros/jazzy/share/rcutils/cmake/rcutilsConfig.cmake",
			"/opt/ros/jazzy/share/rosidl_runtime_c/cmake/ament_cmake_export_dependencies-extras.cmake",
			"/opt/ros/jazzy/share/rosidl_runtime_c/cmake/rosidl_runtime_cConfig.cmake",
			"/opt/ros/jazzy/share/builtin_interfaces/cmake/ament_cmake_export_dependencies-extras.cmake",
			"/opt/ros/jazzy/share/builtin_interfaces/cmake/builtin_interfacesConfig.cmake",
			"/opt/ros/jazzy/share/rosidl_generator_cpp/cmake/rosidl_generator_cpp_generate_interfaces.cmake",
			"/opt/ros/jazzy/share/ament_cmake_ros/cmake/ament_cmake_ros-extras.cmake",
			"/opt/ros/jazzy/share/ament_cmake_ros/cmake/ament_cmake_rosConfig.cmake",
			"/opt/ros/jazzy/share/rosidl_typesupport_fastrtps_c/cmake/rosidl_typesupport_fastrtps_c_generate_interfaces.cmake"
		],
		"nodes" : 
		[
			{
				"file" : 4
			},
			{
				"command" : 4,
				"file" : 4,
				"line" : 8,
				"parent" : 0
			},
			{
				"command" : 3,
				"file" : 3,
				"line" : 280,
				"parent" : 1
			},
			{
				"command" : 2,
				"file" : 2,
				"line" : 48,
				"parent" : 2
			},
			{
				"file" : 1,
				"parent" : 3
			},
			{
				"command" : 1,
				"file" : 1,
				"line" : 103,
				"parent" : 4
			},
			{
				"command" : 0,
				"file" : 0,
				"line" : 655,
				"parent" : 5
			},
			{
				"command" : 7,
				"file" : 1,
				"line" : 157,
				"parent" : 4
			},
			{
				"command" : 6,
				"file" : 6,
				"line" : 37,
				"parent" : 7
			},
			{
				"command" : 5,
				"file" : 5,
				"line" : 50,
				"parent" : 8
			},
			{
				"command" : 8,
				"file" : 1,
				"line" : 134,
				"parent" : 4
			},
			{
				"command" : 8,
				"file" : 1,
				"line" : 146,
				"parent" : 4
			},
			{
				"command" : 8,
				"file" : 1,
				"line" : 146,
				"parent" : 4
			},
			{
				"command" : 8,
				"file" : 1,
				"line" : 146,
				"parent" : 4
			},
			{
				"command" : 8,
				"file" : 1,
				"line" : 146,
				"parent" : 4
			},
			{
				"command" : 8,
				"file" : 1,
				"line" : 138,
				"parent" : 4
			},
			{
				"command" : 2,
				"file" : 2,
				"line" : 48,
				"parent" : 2
			},
			{
				"file" : 7,
				"parent" : 16
			},
			{
				"command" : 8,
				"file" : 7,
				"line" : 165,
				"parent" : 17
			},
			{
				"command" : 8,
				"file" : 7,
				"line" : 165,
				"parent" : 17
			},
			{
				"command" : 8,
				"file" : 7,
				"line" : 165,
				"parent" : 17
			},
			{
				"command" : 8,
				"file" : 7,
				"line" : 165,
				"parent" : 17
			},
			{
				"command" : 8,
				"file" : 7,
				"line" : 170,
				"parent" : 17
			},
			{
				"command" : 11,
				"file" : 4,
				"line" : 5,
				"parent" : 0
			},
			{
				"command" : 10,
				"file" : 0,
				"line" : 910,
				"parent" : 23
			},
			{
				"file" : 14,
				"parent" : 24
			},
			{
				"command" : 2,
				"file" : 14,
				"line" : 41,
				"parent" : 25
			},
			{
				"file" : 13,
				"parent" : 26
			},
			{
				"command" : 11,
				"file" : 13,
				"line" : 21,
				"parent" : 27
			},
			{
				"command" : 10,
				"file" : 0,
				"line" : 910,
				"parent" : 28
			},
			{
				"file" : 12,
				"parent" : 29
			},
			{
				"command" : 2,
				"file" : 12,
				"line" : 41,
				"parent" : 30
			},
			{
				"file" : 11,
				"parent" : 31
			},
			{
				"command" : 11,
				"file" : 11,
				"line" : 21,
				"parent" : 32
			},
			{
				"command" : 10,
				"file" : 0,
				"line" : 910,
				"parent" : 33
			},
			{
				"file" : 10,
				"parent" : 34
			},
			{
				"command" : 2,
				"file" : 10,
				"line" : 41,
				"parent" : 35
			},
			{
				"file" : 9,
				"parent" : 36
			},
			{
				"command" : 2,
				"file" : 9,
				"line" : 9,
				"parent" : 37
			},
			{
				"file" : 8,
				"parent" : 38
			},
			{
				"command" : 9,
				"file" : 8,
				"line" : 61,
				"parent" : 39
			},
			{
				"command" : 2,
				"file" : 2,
				"line" : 48,
				"parent" : 2
			},
			{
				"file" : 15,
				"parent" : 41
			},
			{
				"command" : 12,
				"file" : 15,
				"line" : 164,
				"parent" : 42
			},
			{
				"command" : 13,
				"file" : 1,
				"line" : 114,
				"parent" : 4
			},
			{
				"command" : 2,
				"file" : 2,
				"line" : 48,
				"parent" : 2
			},
			{
				"file" : 18,
				"parent" : 45
			},
			{
				"command" : 11,
				"file" : 18,
				"line" : 21,
				"parent" : 46
			},
			{
				"command" : 10,
				"file" : 0,
				"line" : 910,
				"parent" : 47
			},
			{
				"file" : 17,
				"parent" : 48
			},
			{
				"command" : 2,
				"file" : 17,
				"line" : 41,
				"parent" : 49
			},
			{
				"file" : 16,
				"parent" : 50
			},
			{
				"command" : 14,
				"file" : 16,
				"line" : 25,
				"parent" : 51
			}
		]
	},
	"compileGroups" : 
	[
		{
			"compileCommandFragments" : 
			[
				{
					"fragment" : "-std=gnu++17 -fPIC"
				},
				{
					"backtrace" : 44,
					"fragment" : "-Wall"
				},
				{
					"backtrace" : 44,
					"fragment" : "-Wextra"
				},
				{
					"backtrace" : 44,
					"fragment" : "-Wpedantic"
				}
			],
			"defines" : 
			[
				{
					"define" : "ROSIDL_TYPESUPPORT_CPP_BUILDING_DLL"
				},
				{
					"backtrace" : 52,
					"define" : "ROS_PACKAGE_NAME=\"play_motion2_msgs\""
				}
			],
			"includes" : 
			[
				{
					"backtrace" : 10,
					"path" : "/home/hoangkn/Hoang/Main-Projects/SentinelDrone/bookros2_ws/build/play_motion2_msgs/rosidl_generator_c"
				},
				{
					"backtrace" : 10,
					"path" : "/home/hoangkn/Hoang/Main-Projects/SentinelDrone/bookros2_ws/build/play_motion2_msgs/rosidl_generator_cpp"
				},
				{
					"backtrace" : 10,
					"isSystem" : true,
					"path" : "/opt/ros/jazzy/include/builtin_interfaces"
				},
				{
					"backtrace" : 10,
					"isSystem" : true,
					"path" : "/opt/ros/jazzy/include/rosidl_runtime_c"
				},
				{
					"backtrace" : 10,
					"isSystem" : true,
					"path" : "/opt/ros/jazzy/include/rcutils"
				},
				{
					"backtrace" : 10,
					"isSystem" : true,
					"path" : "/opt/ros/jazzy/include/rosidl_typesupport_interface"
				},
				{
					"backtrace" : 10,
					"isSystem" : true,
					"path" : "/opt/ros/jazzy/include/service_msgs"
				},
				{
					"backtrace" : 10,
					"isSystem" : true,
					"path" : "/opt/ros/jazzy/include/action_msgs"
				},
				{
					"backtrace" : 10,
					"isSystem" : true,
					"path" : "/opt/ros/jazzy/include/unique_identifier_msgs"
				},
				{
					"backtrace" : 10,
					"isSystem" : true,
					"path" : "/opt/ros/jazzy/include/rosidl_runtime_cpp"
				},
				{
					"backtrace" : 15,
					"isSystem" : true,
					"path" : "/opt/ros/jazzy/include/rosidl_typesupport_cpp"
				},
				{
					"backtrace" : 15,
					"isSystem" : true,
					"path" : "/opt/ros/jazzy/include/rosidl_typesupport_c"
				}
			],
			"language" : "CXX",
			"languageStandard" : 
			{
				"backtraces" : 
				[
					10
				],
				"standard" : "17"
			},
			"sourceIndexes" : 
			[
				0,
				1,
				2,
				3,
				4,
				5,
				6
			]
		}
	],
	"dependencies" : 
	[
		{
			"backtrace" : 43,
			"id" : "play_motion2_msgs__cpp::@6890427a1f51a3e7e1df"
		},
		{
			"backtrace" : 10,
			"id" : "play_motion2_msgs__rosidl_generator_c::@6890427a1f51a3e7e1df"
		}
	],
	"id" : "play_motion2_msgs__rosidl_typesupport_cpp::@6890427a1f51a3e7e1df",
	"install" : 
	{
		"destinations" : 
		[
			{
				"backtrace" : 9,
				"path" : "lib"
			},
			{
				"backtrace" : 9,
				"path" : "lib"
			}
		],
		"prefix" : 
		{
			"path" : "/home/hoangkn/Hoang/Main-Projects/SentinelDrone/bookros2_ws/install/play_motion2_msgs"
		}
	},
	"link" : 
	{
		"commandFragments" : 
		[
			{
				"fragment" : "-Wl,--no-undefined",
				"role" : "flags"
			},
			{
				"fragment" : "-Wl,-rpath,/home/hoangkn/Hoang/Main-Projects/SentinelDrone/bookros2_ws/build/play_motion2_msgs:/opt/ros/jazzy/lib:",
				"role" : "libraries"
			},
			{
				"backtrace" : 10,
				"fragment" : "libplay_motion2_msgs__rosidl_generator_c.so",
				"role" : "libraries"
			},
			{
				"backtrace" : 11,
				"fragment" : "/opt/ros/jazzy/lib/libaction_msgs__rosidl_typesupport_cpp.so",
				"role" : "libraries"
			},
			{
				"backtrace" : 12,
				"fragment" : "/opt/ros/jazzy/lib/libunique_identifier_msgs__rosidl_typesupport_cpp.so",
				"role" : "libraries"
			},
			{
				"backtrace" : 13,
				"fragment" : "/opt/ros/jazzy/lib/libservice_msgs__rosidl_typesupport_cpp.so",
				"role" : "libraries"
			},
			{
				"backtrace" : 14,
				"fragment" : "/opt/ros/jazzy/lib/libbuiltin_interfaces__rosidl_typesupport_cpp.so",
				"role" : "libraries"
			},
			{
				"backtrace" : 15,
				"fragment" : "/opt/ros/jazzy/lib/librosidl_typesupport_cpp.so",
				"role" : "libraries"
			},
			{
				"backtrace" : 15,
				"fragment" : "/opt/ros/jazzy/lib/librosidl_typesupport_c.so",
				"role" : "libraries"
			},
			{
				"backtrace" : 18,
				"fragment" : "/opt/ros/jazzy/lib/libaction_msgs__rosidl_generator_c.so",
				"role" : "libraries"
			},
			{
				"backtrace" : 19,
				"fragment" : "/opt/ros/jazzy/lib/libservice_msgs__rosidl_generator_c.so",
				"role" : "libraries"
			},
			{
				"backtrace" : 20,
				"fragment" : "/opt/ros/jazzy/lib/libbuiltin_interfaces__rosidl_generator_c.so",
				"role" : "libraries"
			},
			{
				"backtrace" : 21,
				"fragment" : "/opt/ros/jazzy/lib/libunique_identifier_msgs__rosidl_generator_c.so",
				"role" : "libraries"
			},
			{
				"backtrace" : 15,
				"fragment" : "/opt/ros/jazzy/lib/librosidl_runtime_c.so",
				"role" : "libraries"
			},
			{
				"backtrace" : 22,
				"fragment" : "/opt/ros/jazzy/lib/librcutils.so",
				"role" : "libraries"
			},
			{
				"backtrace" : 40,
				"fragment" : "-ldl",
				"role" : "libraries"
			},
			{
				"backtrace" : 40,
				"fragment" : "-latomic",
				"role" : "libraries"
			},
			{
				"fragment" : "-Wl,-rpath-link,/opt/ros/jazzy/lib",
				"role" : "libraries"
			}
		],
		"language" : "CXX"
	},
	"name" : "play_motion2_msgs__rosidl_typesupport_cpp",
	"nameOnDisk" : "libplay_motion2_msgs__rosidl_typesupport_cpp.so",
	"paths" : 
	{
		"build" : ".",
		"source" : "."
	},
	"sourceGroups" : 
	[
		{
			"name" : "Source Files",
			"sourceIndexes" : 
			[
				0,
				1,
				2,
				3,
				4,
				5,
				6
			]
		},
		{
			"name" : "CMake Rules",
			"sourceIndexes" : 
			[
				7
			]
		}
	],
	"sources" : 
	[
		{
			"backtrace" : 6,
			"compileGroupIndex" : 0,
			"isGenerated" : true,
			"path" : "/home/hoangkn/Hoang/Main-Projects/SentinelDrone/bookros2_ws/build/play_motion2_msgs/rosidl_typesupport_cpp/play_motion2_msgs/action/play_motion2__type_support.cpp",
			"sourceGroupIndex" : 0
		},
		{
			"backtrace" : 6,
			"compileGroupIndex" : 0,
			"isGenerated" : true,
			"path" : "/home/hoangkn/Hoang/Main-Projects/SentinelDrone/bookros2_ws/build/play_motion2_msgs/rosidl_typesupport_cpp/play_motion2_msgs/msg/motion__type_support.cpp",
			"sourceGroupIndex" : 0
		},
		{
			"backtrace" : 6,
			"compileGroupIndex" : 0,
			"isGenerated" : true,
			"path" : "/home/hoangkn/Hoang/Main-Projects/SentinelDrone/bookros2_ws/build/play_motion2_msgs/rosidl_typesupport_cpp/play_motion2_msgs/srv/add_motion__type_support.cpp",
			"sourceGroupIndex" : 0
		},
		{
			"backtrace" : 6,
			"compileGroupIndex" : 0,
			"isGenerated" : true,
			"path" : "/home/hoangkn/Hoang/Main-Projects/SentinelDrone/bookros2_ws/build/play_motion2_msgs/rosidl_typesupport_cpp/play_motion2_msgs/srv/get_motion_info__type_support.cpp",
			"sourceGroupIndex" : 0
		},
		{
			"backtrace" : 6,
			"compileGroupIndex" : 0,
			"isGenerated" : true,
			"path" : "/home/hoangkn/Hoang/Main-Projects/SentinelDrone/bookros2_ws/build/play_motion2_msgs/rosidl_typesupport_cpp/play_motion2_msgs/srv/is_motion_ready__type_support.cpp",
			"sourceGroupIndex" : 0
		},
		{
			"backtrace" : 6,
			"compileGroupIndex" : 0,
			"isGenerated" : true,
			"path" : "/home/hoangkn/Hoang/Main-Projects/SentinelDrone/bookros2_ws/build/play_motion2_msgs/rosidl_typesupport_cpp/play_motion2_msgs/srv/list_motions__type_support.cpp",
			"sourceGroupIndex" : 0
		},
		{
			"backtrace" : 6,
			"compileGroupIndex" : 0,
			"isGenerated" : true,
			"path" : "/home/hoangkn/Hoang/Main-Projects/SentinelDrone/bookros2_ws/build/play_motion2_msgs/rosidl_typesupport_cpp/play_motion2_msgs/srv/remove_motion__type_support.cpp",
			"sourceGroupIndex" : 0
		},
		{
			"backtrace" : 0,
			"isGenerated" : true,
			"path" : "/home/hoangkn/Hoang/Main-Projects/SentinelDrone/bookros2_ws/build/play_motion2_msgs/rosidl_typesupport_cpp/play_motion2_msgs/action/play_motion2__type_support.cpp.rule",
			"sourceGroupIndex" : 1
		}
	],
	"type" : "SHARED_LIBRARY"
}
